
<DOCUMENT>
<TYPE>XML
<SEQUENCE>177
<FILENAME>R141.xml
<DESCRIPTION>IDEA: Noncontrolling Interests (Schedule of Changes in Ownership Interests) (Details)
<TEXT>
<XBRL>
<?xml version="1.0" encoding="utf-8"?>
<InstanceReport xmlns:xsi="http://www.w3.org/2001/XMLSchema-instance" xmlns:xsd="http://www.w3.org/2001/XMLSchema">
  <Version>2.2.0.7</Version>
  <hasSegments>false</hasSegments>
  <ReportName>Noncontrolling Interests (Schedule of Changes in Ownership Interests) (Details) (USD $)</ReportName>
  <ReportLongName>42002 - Disclosure - Noncontrolling Interests (Schedule of Changes in Ownership Interests) (Details)</ReportLongName>
  <DisplayLabelColumn>true</DisplayLabelColumn>
  <ShowElementNames>false</ShowElementNames>
  <RoundingOption>In Millions</RoundingOption>
  <HasEmbeddedReports>false</HasEmbeddedReports>
  <Columns>
    <Column>
      <LabelColumn>false</LabelColumn>
      <Id>1</Id>
      <Labels>
        <Label Id="1" Label="12 Months Ended" />
        <Label Id="2" Label="Sep. 30, 2010" />
      </Labels>
      <CurrencyCode>USD</CurrencyCode>
      <FootnoteIndexer />
      <hasSegments>false</hasSegments>
      <hasScenarios>false</hasScenarios>
      <Segments />
      <Scenarios />
      <Units>
        <Unit>
          <UnitID>Unit1</UnitID>
          <UnitType>Standard</UnitType>
          <StandardMeasure>
            <MeasureSchema>http://www.xbrl.org/2003/iso4217</MeasureSchema>
            <MeasureValue>USD</MeasureValue>
            <MeasureNamespace>iso4217</MeasureNamespace>
          </StandardMeasure>
          <Scale>0</Scale>
        </Unit>
        <Unit>
          <UnitID>Unit13</UnitID>
          <UnitType>Standard</UnitType>
          <StandardMeasure>
            <MeasureSchema>http://www.xbrl.org/2003/instance</MeasureSchema>
            <MeasureValue>pure</MeasureValue>
            <MeasureNamespace>xbrli</MeasureNamespace>
          </StandardMeasure>
          <Scale>0</Scale>
        </Unit>
        <Unit>
          <UnitID>Unit15</UnitID>
          <UnitType>Standard</UnitType>
          <StandardMeasure>
            <MeasureSchema>http://www.xbrl.org/2003/instance</MeasureSchema>
            <MeasureValue>shares</MeasureValue>
            <MeasureNamespace>xbrli</MeasureNamespace>
          </StandardMeasure>
          <Scale>0</Scale>
        </Unit>
        <Unit>
          <UnitID>Unit12</UnitID>
          <UnitType>Divide</UnitType>
          <NumeratorMeasure>
            <MeasureSchema>http://www.xbrl.org/2003/iso4217</MeasureSchema>
            <MeasureValue>USD</MeasureValue>
            <MeasureNamespace>iso4217</MeasureNamespace>
          </NumeratorMeasure>
          <DenominatorMeasure>
            <MeasureSchema>http://www.xbrl.org/2003/instance</MeasureSchema>
            <MeasureValue>shares</MeasureValue>
            <MeasureNamespace>xbrli</MeasureNamespace>
          </DenominatorMeasure>
          <Scale>0</Scale>
        </Unit>
      </Units>
      <CurrencySymbol>$</CurrencySymbol>
    </Column>
    <Column>
      <LabelColumn>false</LabelColumn>
      <Id>2</Id>
      <Labels>
        <Label Id="1" Label="12 Months Ended" />
        <Label Id="2" Label="Sep. 30, 2009" />
      </Labels>
      <CurrencyCode>USD</CurrencyCode>
      <FootnoteIndexer />
      <hasSegments>false</hasSegments>
      <hasScenarios>false</hasScenarios>
      <Segments />
      <Scenarios />
      <Units>
        <Unit>
          <UnitID>Unit1</UnitID>
          <UnitType>Standard</UnitType>
          <StandardMeasure>
            <MeasureSchema>http://www.xbrl.org/2003/iso4217</MeasureSchema>
            <MeasureValue>USD</MeasureValue>
            <MeasureNamespace>iso4217</MeasureNamespace>
          </StandardMeasure>
          <Scale>0</Scale>
        </Unit>
        <Unit>
          <UnitID>Unit13</UnitID>
          <UnitType>Standard</UnitType>
          <StandardMeasure>
            <MeasureSchema>http://www.xbrl.org/2003/instance</MeasureSchema>
            <MeasureValue>pure</MeasureValue>
            <MeasureNamespace>xbrli</MeasureNamespace>
          </StandardMeasure>
          <Scale>0</Scale>
        </Unit>
        <Unit>
          <UnitID>Unit15</UnitID>
          <UnitType>Standard</UnitType>
          <StandardMeasure>
            <MeasureSchema>http://www.xbrl.org/2003/instance</MeasureSchema>
            <MeasureValue>shares</MeasureValue>
            <MeasureNamespace>xbrli</MeasureNamespace>
          </StandardMeasure>
          <Scale>0</Scale>
        </Unit>
        <Unit>
          <UnitID>Unit12</UnitID>
          <UnitType>Divide</UnitType>
          <NumeratorMeasure>
            <MeasureSchema>http://www.xbrl.org/2003/iso4217</MeasureSchema>
            <MeasureValue>USD</MeasureValue>
            <MeasureNamespace>iso4217</MeasureNamespace>
          </NumeratorMeasure>
          <DenominatorMeasure>
            <MeasureSchema>http://www.xbrl.org/2003/instance</MeasureSchema>
            <MeasureValue>shares</MeasureValue>
            <MeasureNamespace>xbrli</MeasureNamespace>
          </DenominatorMeasure>
          <Scale>0</Scale>
        </Unit>
      </Units>
      <CurrencySymbol>$</CurrencySymbol>
    </Column>
    <Column>
      <LabelColumn>false</LabelColumn>
      <Id>3</Id>
      <Labels>
        <Label Id="1" Label="12 Months Ended" />
        <Label Id="2" Label="Sep. 30, 2008" />
      </Labels>
      <CurrencyCode>USD</CurrencyCode>
      <FootnoteIndexer />
      <hasSegments>false</hasSegments>
      <hasScenarios>false</hasScenarios>
      <Segments />
      <Scenarios />
      <Units>
        <Unit>
          <UnitID>Unit1</UnitID>
          <UnitType>Standard</UnitType>
          <StandardMeasure>
            <MeasureSchema>http://www.xbrl.org/2003/iso4217</MeasureSchema>
            <MeasureValue>USD</MeasureValue>
            <MeasureNamespace>iso4217</MeasureNamespace>
          </StandardMeasure>
          <Scale>0</Scale>
        </Unit>
        <Unit>
          <UnitID>Unit15</UnitID>
          <UnitType>Standard</UnitType>
          <StandardMeasure>
            <MeasureSchema>http://www.xbrl.org/2003/instance</MeasureSchema>
            <MeasureValue>shares</MeasureValue>
            <MeasureNamespace>xbrli</MeasureNamespace>
          </StandardMeasure>
          <Scale>0</Scale>
        </Unit>
        <Unit>
          <UnitID>Unit13</UnitID>
          <UnitType>Standard</UnitType>
          <StandardMeasure>
            <MeasureSchema>http://www.xbrl.org/2003/instance</MeasureSchema>
            <MeasureValue>pure</MeasureValue>
            <MeasureNamespace>xbrli</MeasureNamespace>
          </StandardMeasure>
          <Scale>0</Scale>
        </Unit>
        <Unit>
          <UnitID>Unit12</UnitID>
          <UnitType>Divide</UnitType>
          <NumeratorMeasure>
            <MeasureSchema>http://www.xbrl.org/2003/iso4217</MeasureSchema>
            <MeasureValue>USD</MeasureValue>
            <MeasureNamespace>iso4217</MeasureNamespace>
          </NumeratorMeasure>
          <DenominatorMeasure>
            <MeasureSchema>http://www.xbrl.org/2003/instance</MeasureSchema>
            <MeasureValue>shares</MeasureValue>
            <MeasureNamespace>xbrli</MeasureNamespace>
          </DenominatorMeasure>
          <Scale>0</Scale>
        </Unit>
      </Units>
      <CurrencySymbol>$</CurrencySymbol>
    </Column>
  </Columns>
  <Rows>
    <Row>
      <Id>2</Id>
      <Label>Noncontrolling Interest</Label>
      <Level>0</Level>
      <ElementName>us-gaap_MinorityInterestAbstract</ElementName>
      <ElementPrefix>us-gaap</ElementPrefix>
      <IsBaseElement>true</IsBaseElement>
      <BalanceType>na</BalanceType>
      <PeriodType>duration</PeriodType>
      <ShortDefinition>No definition available.</ShortDefinition>
      <IsReportTitle>false</IsReportTitle>
      <IsSegmentTitle>false</IsSegmentTitle>
      <IsSubReportEnd>false</IsSubReportEnd>
      <IsCalendarTitle>false</IsCalendarTitle>
      <IsTuple>false</IsTuple>
      <IsAbstractGroupTitle>true</IsAbstractGroupTitle>
      <IsEquityPrevioslyReportedAsRow>false</IsEquityPrevioslyReportedAsRow>
      <IsEquityAdjustmentRow>false</IsEquityAdjustmentRow>
      <IsBeginningBalance>false</IsBeginningBalance>
      <IsEndingBalance>false</IsEndingBalance>
      <IsReverseSign>false</IsReverseSign>
      <PreferredLabelRole />
      <IsEPS>false</IsEPS>
      <FootnoteIndexer />
      <Cells>
        <Cell>
          <Id>1</Id>
          <ShowCurrencySymbol>false</ShowCurrencySymbol>
          <IsNumeric>false</IsNumeric>
          <IsRatio>false</IsRatio>
          <DisplayZeroAsNone>false</DisplayZeroAsNone>
          <NumericAmount>0</NumericAmount>
          <RoundedNumericAmount>0</RoundedNumericAmount>
          <NonNumbericText />
          <NonNumericTextHeader />
          <FootnoteIndexer />
          <hasSegments>false</hasSegments>
          <hasScenarios>false</hasScenarios>
          <DisplayDateInUSFormat>false</DisplayDateInUSFormat>
        </Cell>
        <Cell>
          <Id>2</Id>
          <ShowCurrencySymbol>false</ShowCurrencySymbol>
          <IsNumeric>false</IsNumeric>
          <IsRatio>false</IsRatio>
          <DisplayZeroAsNone>false</DisplayZeroAsNone>
          <NumericAmount>0</NumericAmount>
          <RoundedNumericAmount>0</RoundedNumericAmount>
          <NonNumbericText />
          <NonNumericTextHeader />
          <FootnoteIndexer />
          <hasSegments>false</hasSegments>
          <hasScenarios>false</hasScenarios>
          <DisplayDateInUSFormat>false</DisplayDateInUSFormat>
        </Cell>
        <Cell>
          <Id>3</Id>
          <ShowCurrencySymbol>false</ShowCurrencySymbol>
          <IsNumeric>false</IsNumeric>
          <IsRatio>false</IsRatio>
          <DisplayZeroAsNone>false</DisplayZeroAsNone>
          <NumericAmount>0</NumericAmount>
          <RoundedNumericAmount>0</RoundedNumericAmount>
          <NonNumbericText />
          <NonNumericTextHeader />
          <FootnoteIndexer />
          <hasSegments>false</hasSegments>
          <hasScenarios>false</hasScenarios>
          <DisplayDateInUSFormat>false</DisplayDateInUSFormat>
        </Cell>
      </Cells>
      <OriginalInstanceReportColumns />
      <ElementDataType>xbrli:stringItemType</ElementDataType>
      <SimpleDataType>string</SimpleDataType>
      <ElementDefenition>No definition available.</ElementDefenition>
      <IsTotalLabel>false</IsTotalLabel>
    </Row>
    <Row>
      <Id>3</Id>
      <Label>Net income attributable to Air Products</Label>
      <Level>1</Level>
      <ElementName>us-gaap_NetIncomeLoss</ElementName>
      <ElementPrefix>us-gaap</ElementPrefix>
      <IsBaseElement>true</IsBaseElement>
      <BalanceType>credit</BalanceType>
      <PeriodType>duration</PeriodType>
      <ShortDefinition>No definition available.</ShortDefinition>
      <IsReportTitle>false</IsReportTitle>
      <IsSegmentTitle>false</IsSegmentTitle>
      <IsSubReportEnd>false</IsSubReportEnd>
      <IsCalendarTitle>false</IsCalendarTitle>
      <IsTuple>false</IsTuple>
      <IsAbstractGroupTitle>false</IsAbstractGroupTitle>
      <IsEquityPrevioslyReportedAsRow>false</IsEquityPrevioslyReportedAsRow>
      <IsEquityAdjustmentRow>false</IsEquityAdjustmentRow>
      <IsBeginningBalance>false</IsBeginningBalance>
      <IsEndingBalance>false</IsEndingBalance>
      <IsReverseSign>false</IsReverseSign>
      <PreferredLabelRole />
      <IsEPS>false</IsEPS>
      <FootnoteIndexer />
      <Cells>
        <Cell>
          <Id>1</Id>
          <ShowCurrencySymbol>true</ShowCurrencySymbol>
          <IsNumeric>true</IsNumeric>
          <IsRatio>false</IsRatio>
          <DisplayZeroAsNone>false</DisplayZeroAsNone>
          <NumericAmount>1029100000</NumericAmount>
          <RoundedNumericAmount>1029.1</RoundedNumericAmount>
          <NonNumbericText />
          <NonNumericTextHeader />
          <FootnoteIndexer />
          <hasSegments>false</hasSegments>
          <hasScenarios>false</hasScenarios>
          <DisplayDateInUSFormat>false</DisplayDateInUSFormat>
        </Cell>
        <Cell>
          <Id>2</Id>
          <ShowCurrencySymbol>true</ShowCurrencySymbol>
          <IsNumeric>true</IsNumeric>
          <IsRatio>false</IsRatio>
          <DisplayZeroAsNone>false</DisplayZeroAsNone>
          <NumericAmount>631300000</NumericAmount>
          <RoundedNumericAmount>631.3</RoundedNumericAmount>
          <NonNumbericText />
          <NonNumericTextHeader />
          <FootnoteIndexer />
          <hasSegments>false</hasSegments>
          <hasScenarios>false</hasScenarios>
          <DisplayDateInUSFormat>false</DisplayDateInUSFormat>
        </Cell>
        <Cell>
          <Id>3</Id>
          <ShowCurrencySymbol>true</ShowCurrencySymbol>
          <IsNumeric>true</IsNumeric>
          <IsRatio>false</IsRatio>
          <DisplayZeroAsNone>false</DisplayZeroAsNone>
          <NumericAmount>909700000</NumericAmount>
          <RoundedNumericAmount>909.7</RoundedNumericAmount>
          <NonNumbericText />
          <NonNumericTextHeader />
          <FootnoteIndexer />
          <hasSegments>false</hasSegments>
          <hasScenarios>false</hasScenarios>
          <DisplayDateInUSFormat>false</DisplayDateInUSFormat>
        </Cell>
      </Cells>
      <OriginalInstanceReportColumns />
      <ElementDataType>xbrli:monetaryItemType</ElementDataType>
      <SimpleDataType>monetary</SimpleDataType>
      <ElementDefenition>The portion of consolidated profit or loss for the period, net of income taxes, which is attributable to the parent. If the entity does not present consolidated financial statements, the amount of profit or loss for the period, net of income taxes.</ElementDefenition>
      <ElementReferences>Reference 1: http://www.xbrl.org/2003/role/presentationRef
 -Publisher SEC
 -Name Regulation S-X (SX)
 -Number 210
 -Section 03
 -Paragraph 19
 -Article 5

Reference 2: http://www.xbrl.org/2003/role/presentationRef
 -Publisher AICPA
 -Name Accounting Research Bulletin (ARB)
 -Number 51
 -Paragraph 38
 -Subparagraph d

Reference 3: http://www.xbrl.org/2003/role/presentationRef
 -Publisher AICPA
 -Name Accounting Research Bulletin (ARB)
 -Number 51
 -Paragraph A7
 -Appendix A

Reference 4: http://www.xbrl.org/2003/role/presentationRef
 -Publisher AICPA
 -Name Accounting Research Bulletin (ARB)
 -Number 51
 -Paragraph 38
 -Subparagraph a

Reference 5: http://www.xbrl.org/2003/role/presentationRef
 -Publisher SEC
 -Name Regulation S-X (SX)
 -Number 210
 -Section 04
 -Paragraph 20
 -Article 9

Reference 6: http://www.xbrl.org/2003/role/presentationRef
 -Publisher FASB
 -Name Statement of Financial Accounting Standard (FAS)
 -Number 130
 -Paragraph 10, 15

Reference 7: http://www.xbrl.org/2003/role/presentationRef
 -Publisher FASB
 -Name Emerging Issues Task Force (EITF)
 -Number 87-21

Reference 8: http://www.xbrl.org/2003/role/presentationRef
 -Publisher FASB
 -Name Statement of Financial Accounting Standard (FAS)
 -Number 95
 -Paragraph 28, 29, 30

</ElementReferences>
      <IsTotalLabel>false</IsTotalLabel>
    </Row>
    <Row>
      <Id>4</Id>
      <Label>Decrease in Air Products capital in excess of par value for purchase of noncontrolling interests</Label>
      <Level>1</Level>
      <ElementName>apd_DecreaseInAirProductsCapitalInExcessOfParValueForPurchaseOfNoncontrollingInterests</ElementName>
      <ElementPrefix>apd</ElementPrefix>
      <IsBaseElement>false</IsBaseElement>
      <BalanceType>debit</BalanceType>
      <PeriodType>duration</PeriodType>
      <ShortDefinition>Decrease In Air Products Capital In Excess Of Par Value For Purchase Of Noncontrolling Interests</ShortDefinition>
      <IsReportTitle>false</IsReportTitle>
      <IsSegmentTitle>false</IsSegmentTitle>
      <IsSubReportEnd>false</IsSubReportEnd>
      <IsCalendarTitle>false</IsCalendarTitle>
      <IsTuple>false</IsTuple>
      <IsAbstractGroupTitle>false</IsAbstractGroupTitle>
      <IsEquityPrevioslyReportedAsRow>false</IsEquityPrevioslyReportedAsRow>
      <IsEquityAdjustmentRow>false</IsEquityAdjustmentRow>
      <IsBeginningBalance>false</IsBeginningBalance>
      <IsEndingBalance>false</IsEndingBalance>
      <IsReverseSign>true</IsReverseSign>
      <PreferredLabelRole>negated</PreferredLabelRole>
      <IsEPS>false</IsEPS>
      <FootnoteIndexer />
      <Cells>
        <Cell>
          <Id>1</Id>
          <ShowCurrencySymbol>false</ShowCurrencySymbol>
          <IsNumeric>true</IsNumeric>
          <IsRatio>false</IsRatio>
          <DisplayZeroAsNone>false</DisplayZeroAsNone>
          <NumericAmount>-28300000</NumericAmount>
          <RoundedNumericAmount>-28.3</RoundedNumericAmount>
          <NonNumbericText />
          <NonNumericTextHeader />
          <FootnoteIndexer />
          <hasSegments>false</hasSegments>
          <hasScenarios>false</hasScenarios>
          <DisplayDateInUSFormat>false</DisplayDateInUSFormat>
        </Cell>
        <Cell>
          <Id>2</Id>
          <ShowCurrencySymbol>false</ShowCurrencySymbol>
          <IsNumeric>false</IsNumeric>
          <IsRatio>false</IsRatio>
          <DisplayZeroAsNone>false</DisplayZeroAsNone>
          <NumericAmount>0</NumericAmount>
          <RoundedNumericAmount>0</RoundedNumericAmount>
          <NonNumbericText />
          <NonNumericTextHeader />
          <FootnoteIndexer />
          <hasSegments>false</hasSegments>
          <hasScenarios>false</hasScenarios>
          <DisplayDateInUSFormat>false</DisplayDateInUSFormat>
        </Cell>
        <Cell>
          <Id>3</Id>
          <ShowCurrencySymbol>false</ShowCurrencySymbol>
          <IsNumeric>false</IsNumeric>
          <IsRatio>false</IsRatio>
          <DisplayZeroAsNone>false</DisplayZeroAsNone>
          <NumericAmount>0</NumericAmount>
          <RoundedNumericAmount>0</RoundedNumericAmount>
          <NonNumbericText />
          <NonNumericTextHeader />
          <FootnoteIndexer />
          <hasSegments>false</hasSegments>
          <hasScenarios>false</hasScenarios>
          <DisplayDateInUSFormat>false</DisplayDateInUSFormat>
        </Cell>
      </Cells>
      <OriginalInstanceReportColumns />
      <ElementDataType>xbrli:monetaryItemType</ElementDataType>
      <SimpleDataType>monetary</SimpleDataType>
      <ElementDefenition>Decrease In Air Products Capital In Excess Of Par Value For Purchase Of Noncontrolling Interests</ElementDefenition>
      <ElementReferences>No authoritative reference available.</ElementReferences>
      <IsTotalLabel>false</IsTotalLabel>
    </Row>
    <Row>
      <Id>5</Id>
      <Label>Changes from net income attributable to Air Products and transfers to noncontrolling interests</Label>
      <Level>1</Level>
      <ElementName>apd_ChangesFromNetIncomeAndTransfersToNoncontrollingInterests</ElementName>
      <ElementPrefix>apd</ElementPrefix>
      <IsBaseElement>false</IsBaseElement>
      <BalanceType>credit</BalanceType>
      <PeriodType>duration</PeriodType>
      <ShortDefinition>Changes from net income and transfers to noncontrolling interests</ShortDefinition>
      <IsReportTitle>false</IsReportTitle>
      <IsSegmentTitle>false</IsSegmentTitle>
      <IsSubReportEnd>false</IsSubReportEnd>
      <IsCalendarTitle>false</IsCalendarTitle>
      <IsTuple>false</IsTuple>
      <IsAbstractGroupTitle>false</IsAbstractGroupTitle>
      <IsEquityPrevioslyReportedAsRow>false</IsEquityPrevioslyReportedAsRow>
      <IsEquityAdjustmentRow>false</IsEquityAdjustmentRow>
      <IsBeginningBalance>false</IsBeginningBalance>
      <IsEndingBalance>false</IsEndingBalance>
      <IsReverseSign>false</IsReverseSign>
      <PreferredLabelRole>totallabel</PreferredLabelRole>
      <IsEPS>false</IsEPS>
      <FootnoteIndexer />
      <Cells>
        <Cell>
          <Id>1</Id>
          <ShowCurrencySymbol>true</ShowCurrencySymbol>
          <IsNumeric>true</IsNumeric>
          <IsRatio>false</IsRatio>
          <DisplayZeroAsNone>false</DisplayZeroAsNone>
          <NumericAmount>1000800000</NumericAmount>
          <RoundedNumericAmount>1000.8</RoundedNumericAmount>
          <NonNumbericText />
          <NonNumericTextHeader />
          <FootnoteIndexer />
          <hasSegments>false</hasSegments>
          <hasScenarios>false</hasScenarios>
          <DisplayDateInUSFormat>false</DisplayDateInUSFormat>
        </Cell>
        <Cell>
          <Id>2</Id>
          <ShowCurrencySymbol>true</ShowCurrencySymbol>
          <IsNumeric>true</IsNumeric>
          <IsRatio>false</IsRatio>
          <DisplayZeroAsNone>false</DisplayZeroAsNone>
          <NumericAmount>631300000</NumericAmount>
          <RoundedNumericAmount>631.3</RoundedNumericAmount>
          <NonNumbericText />
          <NonNumericTextHeader />
          <FootnoteIndexer />
          <hasSegments>false</hasSegments>
          <hasScenarios>false</hasScenarios>
          <DisplayDateInUSFormat>false</DisplayDateInUSFormat>
        </Cell>
        <Cell>
          <Id>3</Id>
          <ShowCurrencySymbol>true</ShowCurrencySymbol>
          <IsNumeric>true</IsNumeric>
          <IsRatio>false</IsRatio>
          <DisplayZeroAsNone>false</DisplayZeroAsNone>
          <NumericAmount>909700000</NumericAmount>
          <RoundedNumericAmount>909.7</RoundedNumericAmount>
          <NonNumbericText />
          <NonNumericTextHeader />
          <FootnoteIndexer />
          <hasSegments>false</hasSegments>
          <hasScenarios>false</hasScenarios>
          <DisplayDateInUSFormat>false</DisplayDateInUSFormat>
        </Cell>
      </Cells>
      <OriginalInstanceReportColumns />
      <ElementDataType>xbrli:monetaryItemType</ElementDataType>
      <SimpleDataType>monetary</SimpleDataType>
      <ElementDefenition>Changes from net income and transfers to noncontrolling interests</ElementDefenition>
      <ElementReferences>No authoritative reference available.</ElementReferences>
      <IsTotalLabel>true</IsTotalLabel>
    </Row>
  </Rows>
  <Footnotes />
  <NumberOfCols>3</NumberOfCols>
  <NumberOfRows>4</NumberOfRows>
  <HasScenarios>false</HasScenarios>
  <MonetaryRoundingLevel>HundredThousands</MonetaryRoundingLevel>
  <SharesRoundingLevel>UnKnown</SharesRoundingLevel>
  <PerShareRoundingLevel>UnKnown</PerShareRoundingLevel>
  <HasPureData>false</HasPureData>
  <SharesShouldBeRounded>true</SharesShouldBeRounded>
</InstanceReport>
</XBRL>
</TEXT>

</DOCUMENT>